{"bones":[{"name":"root"},{"name":"bone","parent":"root","length":77.07,"x":3.67,"y":-28.6,"rotation":87.54},{"name":"bone2","parent":"root","length":87.99,"x":-39.49,"y":-46,"rotation":-0.38}],"slots":[{"name":"wind_bg","bone":"bone2","attachment":"wind_bg"},{"name":"wind","bone":"bone","attachment":"wind"}],"skins":{"default":{"wind":{"wind":{"x":25.98,"y":0.63,"rotation":-87.54,"width":150,"height":130}},"wind_bg":{"wind_bg":{"x":43.38,"y":43.65,"rotation":0.38,"width":180,"height":180}}}},"animations":{"idle":{"bones":{"root":{"rotate":[{"time":0,"angle":0,"curve":"stepped"},{"time":0.8,"angle":0}],"translate":[{"time":0,"x":0,"y":0},{"time":0.2,"x":0,"y":-6},{"time":0.6,"x":0,"y":7.29},{"time":0.8,"x":0,"y":0}]},"bone":{"rotate":[{"time":0,"angle":-0.54},{"time":0.1,"angle":5.45},{"time":0.2,"angle":-0.54},{"time":0.3,"angle":5.45},{"time":0.4,"angle":-0.54},{"time":0.5,"angle":5.45},{"time":0.6,"angle":-0.54},{"time":0.7,"angle":5.45},{"time":0.8,"angle":-0.54}]}}}}}